{"state":true,"balance":11350,"movements":[{"sale_id":0,"user":"UserVersion","type":1001,"amount":8999,"balance":8999,"dte_code":0,"dte_number":0,"date":"2023-05-10T19:37:24.632Z"},{"sale_id":0,"user":"UserVersion","type":1002,"amount":1,"balance":9000,"dte_code":0,"dte_number":0,"date":"2023-05-10T19:37:38.425Z"},{"sale_id":1055,"user":"UserVersion","type":1004,"amount":450,"balance":9450,"dte_code":0,"dte_number":0,"date":"2023-05-10T19:38:38.306Z"},{"sale_id":1056,"user":"UserVersion","type":1004,"amount":450,"balance":9900,"dte_code":0,"dte_number":0,"date":"2023-05-10T19:39:25.138Z"},{"sale_id":1057,"user":"UserVersion","type":1004,"amount":450,"balance":10350,"dte_code":0,"dte_number":0,"date":"2023-05-10T19:40:34.950Z"},{"sale_id":1058,"user":"UserVersion","type":1004,"amount":1000,"balance":11350,"dte_code":0,"dte_number":0,"date":"2023-05-10T19:42:14.462Z"}]}